axiom_archon/__init__.py
axiom_archon/human_loop.py
axiom_archon/interface.py
axiom_archon/llm_strategic_reviewer.py
axiom_archon/model.py
axiom_archon/rule_based_reviewer.py
axiom_archon/strategic_review_models.py
axiom_canon/__init__.py
axiom_canon/analysis_executor.py
axiom_canon/bfm.py
axiom_canon/cpkg.py
axiom_canon/diff.py
axiom_canon/discovery.py
axiom_canon/documentation.py
axiom_canon/query.py
axiom_canon/readiness.py
axiom_canon/serialization.py
axiom_canon/task_graph.py
axiom_canon/ucir.py
axiom_canon/validation.py
axiom_canon/versioning.py
axiom_canon/ingestion/__init__.py
axiom_canon/ingestion/consumption.py
axiom_canon/ingestion/diffing.py
axiom_canon/ingestion/enrichment.py
axiom_canon/ingestion/enrichment_models.py
axiom_canon/ingestion/extractor.py
axiom_canon/ingestion/models.py
axiom_cli/__init__.py
axiom_cli/copilot_templates.py
axiom_cli/ide_surface.py
axiom_cli/main.py
axiom_cli/output.py
axiom_cli/preconditions.py
axiom_cli/rich_output.py
axiom_cli/tui.py
axiom_cli/workflow_state.py
axiom_conductor/__init__.py
axiom_conductor/context.py
axiom_conductor/events.py
axiom_conductor/executor.py
axiom_conductor/interface.py
axiom_conductor/model.py
axiom_conductor/registry.py
axiom_conductor/registry_models.py
axiom_conductor/remote_dispatch.py
axiom_conductor/selector.py
axiom_conductor/transitions.py
axiom_core/__init__.py
axiom_core/human_decision_intake.py
axiom_core/workflow.py
axiom_engine-1.0.0.dist-info/licenses/LICENSE-AGPL
axiom_engine-1.0.0.dist-info/licenses/LICENSE-COMMERCIAL
axiom_forge/__init__.py
axiom_forge/backend.py
axiom_forge/context_aware_backend.py
axiom_forge/context_aware_models.py
axiom_forge/mock_backend.py
axiom_forge/playwright_backend.py
axiom_forge/remote_auth.py
axiom_forge/remote_protocol.py
axiom_forge/remote_stub.py
axiom_forge/shell_backend.py
axiom_interface/__init__.py
axiom_interface/decision_display.py
axiom_interface/visualization.py
axiom_interface/workflow_guide.py
axiom_logos/__init__.py
axiom_onboarding/__init__.py
axiom_onboarding/configuration.py
axiom_onboarding/existing_project.py
axiom_engine-1.0.0.dist-info/METADATA
axiom_engine-1.0.0.dist-info/WHEEL
axiom_engine-1.0.0.dist-info/entry_points.txt
axiom_engine-1.0.0.dist-info/top_level.txt
axiom_engine-1.0.0.dist-info/RECORD
