Metadata-Version: 2.4
Name: axiom-engine
Version: 1.0.0
Summary: Axiom — Governed AI for Coherent Software Engineering
Author-email: Ramsanjiev <ramsanjiev@gmail.com>
License: Dual License: AGPL-3.0-or-later OR Commercial
Project-URL: Homepage, https://github.com/ramsanjiev/axiom-core
Project-URL: Documentation, https://github.com/ramsanjiev/axiom-core#readme
Project-URL: Repository, https://github.com/ramsanjiev/axiom-core.git
Project-URL: Issues, https://github.com/ramsanjiev/axiom-core/issues
Project-URL: Changelog, https://github.com/ramsanjiev/axiom-core/blob/main/CHANGELOG.md
Keywords: ai,governance,software-engineering,multi-agent,cli
Classifier: Development Status :: 5 - Production/Stable
Classifier: Environment :: Console
Classifier: Intended Audience :: Developers
Classifier: License :: OSI Approved :: GNU Affero General Public License v3 or later (AGPLv3+)
Classifier: Operating System :: OS Independent
Classifier: Programming Language :: Python :: 3
Classifier: Programming Language :: Python :: 3.10
Classifier: Programming Language :: Python :: 3.11
Classifier: Programming Language :: Python :: 3.12
Classifier: Topic :: Software Development :: Libraries :: Application Frameworks
Classifier: Topic :: Software Development :: Quality Assurance
Classifier: Typing :: Typed
Requires-Python: >=3.10
License-File: LICENSE-AGPL
License-File: LICENSE-COMMERCIAL
Requires-Dist: pydantic<3.0.0,>=2.0.0
Provides-Extra: dev
Requires-Dist: pytest<9.0.0,>=7.0.0; extra == "dev"
Requires-Dist: black<25.0.0,>=23.0.0; extra == "dev"
Requires-Dist: isort<6.0.0,>=5.0.0; extra == "dev"
Requires-Dist: mypy<2.0.0,>=1.0.0; extra == "dev"
Requires-Dist: ruff<1.0.0,>=0.1.0; extra == "dev"
Provides-Extra: playwright
Requires-Dist: playwright<2.0.0,>=1.40.0; extra == "playwright"
Provides-Extra: llm
Requires-Dist: openai<2.0.0,>=1.0.0; extra == "llm"
Requires-Dist: anthropic<1.0.0,>=0.18.0; extra == "llm"
Provides-Extra: all
Requires-Dist: axiom-engine[llm,playwright]; extra == "all"
Dynamic: license-file
